{
    "times": [
        0.0,
        1.1111111111111112,
        2.2222222222222223,
        3.3333333333333335,
        4.444444444444445,
        5.555555555555555,
        6.666666666666667,
        7.777777777777779,
        8.88888888888889,
        10.0
    ],
    "n_shells": 14,
    "species": [
        "S",
        "N",
        "D"
    ],
    "Hmid": [
        225.0,
        275.0,
        325.0,
        375.0,
        425.0,
        475.0,
        525.0,
        575.0,
        625.0,
        675.0,
        725.0,
        775.0,
        825.0,
        875.0
    ],
    "max_altitude": 900,
    "min_altitude": 200,
    "population_data": [
        {
            "species": "S",
            "shell": 1,
            "populations": [
                0.0,
                0.0,
                0.0,
                0.0,
                0.0,
                0.0,
                0.0,
                0.0,
                0.0,
                0.0
            ]
        },
        {
            "species": "S",
            "shell": 2,
            "populations": [
                0.0,
                0.0,
                0.0,
                0.0,
                0.0,
                0.0,
                0.0,
                0.0,
                0.0,
                0.0
            ]
        },
        {
            "species": "S",
            "shell": 3,
            "populations": [
                0.0,
                0.0,
                0.0,
                0.0,
                0.0,
                0.0,
                0.0,
                0.0,
                0.0,
                0.0
            ]
        },
        {
            "species": "S",
            "shell": 4,
            "populations": [
                0.0,
                0.0,
                0.0,
                0.0,
                0.0,
                0.0,
                0.0,
                0.0,
                0.0,
                0.0
            ]
        },
        {
            "species": "S",
            "shell": 5,
            "populations": [
                0.0,
                0.0,
                0.0,
                0.0,
                0.0,
                0.0,
                0.0,
                0.0,
                0.0,
                0.0
            ]
        },
        {
            "species": "S",
            "shell": 6,
            "populations": [
                0.0,
                0.0,
                0.0,
                0.0,
                0.0,
                0.0,
                0.0,
                0.0,
                0.0,
                0.0
            ]
        },
        {
            "species": "S",
            "shell": 7,
            "populations": [
                1632.0,
                1420.3549239856238,
                1236.1589692559874,
                1075.8527145170528,
                936.3352529142835,
                814.9104226979575,
                709.2325011883942,
                617.2576968042246,
                537.209842266632,
                467.54475617382707
            ]
        },
        {
            "species": "S",
            "shell": 8,
            "populations": [
                530.0,
                461.2687035366772,
                401.45115731339797,
                349.39148120131546,
                304.0827514893913,
                264.64947446915414,
                230.3299402715264,
                200.46047270480454,
                174.46429177518974,
                151.83994387954326
            ]
        },
        {
            "species": "S",
            "shell": 9,
            "populations": [
                0.0,
                0.0,
                0.0,
                0.0,
                0.0,
                0.0,
                0.0,
                0.0,
                0.0,
                0.0
            ]
        },
        {
            "species": "S",
            "shell": 10,
            "populations": [
                0.0,
                0.0,
                0.0,
                0.0,
                0.0,
                0.0,
                0.0,
                0.0,
                0.0,
                0.0
            ]
        },
        {
            "species": "S",
            "shell": 11,
            "populations": [
                0.0,
                0.0,
                0.0,
                0.0,
                0.0,
                0.0,
                0.0,
                0.0,
                0.0,
                0.0
            ]
        },
        {
            "species": "S",
            "shell": 12,
            "populations": [
                0.0,
                0.0,
                0.0,
                0.0,
                0.0,
                0.0,
                0.0,
                0.0,
                0.0,
                0.0
            ]
        },
        {
            "species": "S",
            "shell": 13,
            "populations": [
                0.0,
                0.0,
                0.0,
                0.0,
                0.0,
                0.0,
                0.0,
                0.0,
                0.0,
                0.0
            ]
        },
        {
            "species": "S",
            "shell": 14,
            "populations": [
                0.0,
                0.0,
                0.0,
                0.0,
                0.0,
                0.0,
                0.0,
                0.0,
                0.0,
                0.0
            ]
        },
        {
            "species": "N",
            "shell": 1,
            "populations": [
                4.0,
                0.41075171082933476,
                0.2801602190527539,
                0.2219608391252003,
                0.18884260086951402,
                0.16855367709807226,
                0.1552098511857934,
                0.14584317184906812,
                0.13895361979860793,
                0.13365321089092147
            ]
        },
        {
            "species": "N",
            "shell": 2,
            "populations": [
                9.0,
                1.57319035224156,
                1.0735008520967622,
                0.8506145906406283,
                0.7237623172830352,
                0.6460405672319508,
                0.5949191100064072,
                0.5590311509736663,
                0.5326317424512373,
                0.5123203204489477
            ]
        },
        {
            "species": "N",
            "shell": 3,
            "populations": [
                29.0,
                4.682087999023534,
                3.2003948420081336,
                2.537266711936656,
                2.159637111878152,
                1.92815789066224,
                1.7758495611206924,
                1.6688890025317005,
                1.5901802705739119,
                1.5296077568188127
            ]
        },
        {
            "species": "N",
            "shell": 4,
            "populations": [
                83.0,
                11.731488462364355,
                8.059719563337007,
                6.399929992639938,
                5.453082312917439,
                4.871876118001157,
                4.48905505821006,
                4.219927409229729,
                4.021675582521756,
                3.8689928500586235
            ]
        },
        {
            "species": "N",
            "shell": 5,
            "populations": [
                127.0,
                29.12368475196423,
                20.260453158093362,
                16.1529139243923,
                13.799336787151628,
                12.349509503014374,
                11.391984454957054,
                10.717007515952927,
                10.218455414834633,
                9.83377007427617
            ]
        },
        {
            "species": "N",
            "shell": 6,
            "populations": [
                164.0,
                64.12146976102011,
                45.95474746720688,
                37.011276312380836,
                31.828708436075075,
                28.60682851704205,
                26.463720479840244,
                24.94241404858069,
                23.811064535113076,
                22.933734779356467
            ]
        },
        {
            "species": "N",
            "shell": 7,
            "populations": [
                189.0,
                127.79616411136162,
                96.90009591546463,
                79.85666827928301,
                69.71774055897707,
                63.27320657598183,
                58.9072847792016,
                55.75557555116009,
                53.37425839165975,
                51.50418372410701
            ]
        },
        {
            "species": "N",
            "shell": 8,
            "populations": [
                291.0,
                218.53679339166737,
                178.179875239311,
                154.40702997974964,
                139.47444213696625,
                129.4889127143031,
                122.40238817407749,
                117.07714580003305,
                112.90057984304973,
                109.50532470901031
            ]
        },
        {
            "species": "N",
            "shell": 9,
            "populations": [
                351.0,
                321.49656640087375,
                299.1058423353573,
                281.85602635575106,
                268.32909069465984,
                257.5093688193952,
                248.66611977646255,
                241.26951317239846,
                234.94062984606344,
                229.40633753421264
            ]
        },
        {
            "species": "N",
            "shell": 10,
            "populations": [
                505.0,
                494.2620171387058,
                484.31651408934584,
                475.0239262057633,
                466.27067141036713,
                457.9649031544898,
                450.03253813652276,
                442.4138922581698,
                435.06137777831333,
                427.93719791727574
            ]
        },
        {
            "species": "N",
            "shell": 11,
            "populations": [
                876.0,
                864.7148241974533,
                853.2158926461799,
                841.5586670892593,
                829.7923739861587,
                817.9605286598828,
                806.101512342458,
                794.2491153712745,
                782.4329322488962,
                770.6787865015168
            ]
        },
        {
            "species": "N",
            "shell": 12,
            "populations": [
                1286.0,
                1261.3630125334546,
                1237.5457755286175,
                1214.5108931519305,
                1192.222886349301,
                1170.6481175507297,
                1149.7546895378298,
                1129.5123439564327,
                1109.8923888822264,
                1090.8676173241856
            ]
        },
        {
            "species": "N",
            "shell": 13,
            "populations": [
                1281.0,
                1267.902254965505,
                1254.8497972270618,
                1241.847822417344,
                1228.901264731068,
                1216.0148035142663,
                1203.1928736511695,
                1190.4396763516063,
                1177.7591866480202,
                1165.155162046662
            ]
        },
        {
            "species": "N",
            "shell": 14,
            "populations": [
                1092.0,
                1073.113887396066,
                1054.5719934721967,
                1036.3677027069248,
                1018.4945277428811,
                1000.9461084974799,
                983.7162093489778,
                966.7987160354452,
                950.1876338047684,
                933.8770851638246
            ]
        },
        {
            "species": "D",
            "shell": 1,
            "populations": [
                0.0,
                0.0234889840777527,
                0.041138312229647415,
                0.04327028082384627,
                0.04040305411466358,
                0.03621207163919255,
                0.031926436264879725,
                0.02798257502765359,
                0.024458391085269482,
                0.021363386817773822
            ]
        },
        {
            "species": "D",
            "shell": 2,
            "populations": [
                0.0,
                0.09024670433408173,
                0.15775034378510935,
                0.165863919892623,
                0.15485551897510566,
                0.1387864249580969,
                0.1223591814980253,
                0.1072433302478756,
                0.09373670518068453,
                0.08187535656972965
            ]
        },
        {
            "species": "D",
            "shell": 3,
            "populations": [
                0.0,
                0.2718292450418059,
                0.47165680937946775,
                0.49521050096807534,
                0.46214081448482963,
                0.41411633430575223,
                0.3650759479288881,
                0.31996578300709144,
                0.2796660963239022,
                0.2442802396446113
            ]
        },
        {
            "species": "D",
            "shell": 4,
            "populations": [
                0.0,
                0.705490565783198,
                1.198012119738739,
                1.2525602479950533,
                1.1673969074735726,
                1.045567079297706,
                0.9215680429009606,
                0.8076215984446851,
                0.7058868889777223,
                0.6165930619310407
            ]
        },
        {
            "species": "D",
            "shell": 5,
            "populations": [
                0.0,
                1.90676317280007,
                3.0760505826225573,
                3.1830537487436095,
                2.957080018612198,
                2.6452212025865443,
                2.3303683780986586,
                2.041767786858938,
                1.7844810939123177,
                1.5588845297043517
            ]
        },
        {
            "species": "D",
            "shell": 6,
            "populations": [
                0.0,
                5.095240399808447,
                7.341996341508856,
                7.4141676799505785,
                6.834254128810227,
                6.095168380991042,
                5.363226789495961,
                4.69644522864838,
                4.104204823069179,
                3.5861822450478886
            ]
        },
        {
            "species": "D",
            "shell": 7,
            "populations": [
                0.0,
                14.473298982199104,
                17.16431061999266,
                16.52905357275119,
                14.994315183480838,
                13.289083770881644,
                11.663611376628547,
                10.202198385077176,
                8.914538827494463,
                7.793978044017018
            ]
        },
        {
            "species": "D",
            "shell": 8,
            "populations": [
                0.0,
                5.790002685565508,
                7.972252306199766,
                8.436292941256024,
                8.128628205788454,
                7.511091996774372,
                6.807431307088457,
                6.124387486395614,
                5.503239993566169,
                4.957490993103914
            ]
        },
        {
            "species": "D",
            "shell": 9,
            "populations": [
                0.0,
                0.18048577852864087,
                0.34658446575588964,
                0.5105698947542174,
                0.679360194362064,
                0.8565695727055276,
                1.0438425146454438,
                1.241668099456052,
                1.4497992221327647,
                1.6675961181290047
            ]
        },
        {
            "species": "D",
            "shell": 10,
            "populations": [
                0.0,
                0.4036727232744235,
                0.8244583602923807,
                1.2619956601697135,
                1.715517237166341,
                2.1839740782826844,
                2.666139330250732,
                3.160688411614748,
                3.6662502197460007,
                4.18145460708982
            ]
        },
        {
            "species": "D",
            "shell": 11,
            "populations": [
                0.0,
                1.1804171564559551,
                2.3728182683436936,
                3.5736584219952126,
                4.779851627008702,
                5.988729929205261,
                7.197998812911276,
                8.405695337046913,
                9.610157612113367,
                10.809992058127248
            ]
        },
        {
            "species": "D",
            "shell": 12,
            "populations": [
                0.0,
                2.460757725808447,
                4.86300525414059,
                7.210203098931675,
                9.505628642836964,
                11.75238341439624,
                13.953402879149312,
                16.1114663016996,
                18.229203838783043,
                20.309104541723915
            ]
        },
        {
            "species": "D",
            "shell": 13,
            "populations": [
                0.0,
                2.434971423993446,
                4.867644142363543,
                7.297479954098376,
                9.723968316999843,
                12.1466260200859,
                14.56499644755673,
                16.978648792324513,
                19.387177562931296,
                21.790201998008964
            ]
        },
        {
            "species": "D",
            "shell": 14,
            "populations": [
                0.0,
                1.7260835136046901,
                3.410559622754242,
                5.054037896056886,
                6.657120512841695,
                8.220402276791441,
                9.74447074573575,
                11.229906378743859,
                12.677282616955472,
                14.08716598660277
            ]
        }
    ],
    "launch": [
        {
            "species": "S",
            "counts": [
                2162.0,
                1881.623627522301,
                1637.6101265693853,
                1425.2441957183682,
                1240.4180044036748,
                1079.5598971671116,
                939.5624414599206,
                817.7181695090292,
                711.6741340418217,
                619.3847000533704
            ]
        }
    ]
}